EasyDiff/__init__.py
EasyDiff/ad.py
EasyDiff/rev_var.py
EasyDiff/var.py
tests/__init__.py
tests/test_ad.py
tests/test_rev_ad.py
tests/test_rev_var.py
tests/test_var.py
easydiff-0.0.3.dist-info/LICENSE
easydiff-0.0.3.dist-info/METADATA
easydiff-0.0.3.dist-info/WHEEL
easydiff-0.0.3.dist-info/top_level.txt
easydiff-0.0.3.dist-info/RECORD
