Metadata-Version: 2.1
Name: easydiff
Version: 0.0.3
Summary: An automatic differentiation library (support forward and reverse mode)
Home-page: https://github.com/CrackAD/cs207-FinalProject
Author: Yang Zhou, Ruby Zhang, Kangli Wu, and Emily Gould
Author-email: yangzhou@g.harvard.edu, yiqingzhang@fas.harvard.edu, kangliwu@hsph.harvard.edu, egould@mba2020.hbs.edu
License: UNKNOWN
Platform: UNKNOWN
Classifier: Programming Language :: Python :: 3
Classifier: License :: OSI Approved :: MIT License
Classifier: Operating System :: OS Independent
Requires-Python: >=3.6
